.bandit
.flake8
.gitignore
.pylintrc
.travis.yml
LICENSE.txt
Makefile
README.md
codecov.yml
dummy.py
rf_python_usage.gif
setup.py
.github/workflows/ci.yml
.vscode/launch.json
.vscode/settings.json
rfpython/__about__.py
rfpython/__init__.py
rfpython.egg-info/PKG-INFO
rfpython.egg-info/SOURCES.txt
rfpython.egg-info/dependency_links.txt
rfpython.egg-info/entry_points.txt
rfpython.egg-info/top_level.txt
test/test_dev.py