Metadata-Version: 2.1
Name: rfpython
Version: 0.0.3
Summary: Run python function utility
Home-page: https://github.com/caiofcm/rfpython
Author: Caio Curitiba Marcellos
Author-email: caiocuritiba@gmail.com
License: License :: OSI Approved :: MIT License
Platform: any
Classifier: Development Status :: 5 - Production/Stable
Classifier: License :: OSI Approved :: MIT License
Classifier: Intended Audience :: Science/Research
Classifier: Operating System :: OS Independent
Classifier: Programming Language :: Python
Classifier: Programming Language :: Python :: 3
Classifier: Topic :: Scientific/Engineering
Classifier: Topic :: Utilities
Requires-Python: >=3
